hyperion/__init__.py
hyperion/hyperion_stream_client.py
hyperion/types.py
hyperion_stream_client-1.0.1.dist-info/LICENSE
hyperion_stream_client-1.0.1.dist-info/METADATA
hyperion_stream_client-1.0.1.dist-info/WHEEL
hyperion_stream_client-1.0.1.dist-info/top_level.txt
hyperion_stream_client-1.0.1.dist-info/RECORD
