Metadata-Version: 2.1
Name: hyperion-stream-client
Version: 1.0.1
Summary: Streaming Client for Hyperion History API
Home-page: https://github.com/debugtitan/hyperion-stream-client.git
Author: Uche David
Author-email: alts.devs@gmail.com
License: MIT
Classifier: Programming Language :: Python :: 3
Classifier: License :: OSI Approved :: MIT License
Classifier: Operating System :: OS Independent
License-File: LICENSE
Requires-Dist: requests
Requires-Dist: python-socketio[asyncio_client]
Requires-Dist: loguru
